[
  {
    "student_email": "ananya@student.com",
    "mentor_email": "harsha@mentor.com",
    "status": "active"
  },
  {
    "student_email": "vikram@student.com",
    "mentor_email": "arjun@mentor.com",
    "status": "active"
  },
  {
    "student_email": "divya_student@student.com",
    "mentor_email": "pranav@mentor.com",
    "status": "active"
  },
  {
    "student_email": "kiran@student.com",
    "mentor_email": "alok@mentor.com",
    "status": "active"
  },
  {
    "student_email": "rahul_student@student.com",
    "mentor_email": "divya@mentor.com",
    "status": "active"
  },
  {
    "student_email": "meera_student@student.com",
    "mentor_email": "meera@mentor.com",
    "status": "active"
  },
  {
    "student_email": "harini@student.com",
    "mentor_email": "rohan@mentor.com",
    "status": "active"
  },
  {
    "student_email": "pooja_student@student.com",
    "mentor_email": "ritu@mentor.com",
    "status": "active"
  },
  {
    "student_email": "rahul_student@student.com",
    "mentor_email": "deepak@mentor.com",
    "status": "active"
  },
  {
    "student_email": "sid@student.com",
    "mentor_email": "tarun@mentor.com",
    "status": "paused"
  },
  {
    "student_email": "meera_student@student.com",
    "mentor_email": "swati@mentor.com",
    "status": "completed"
  },
  {
    "student_email": "aditya@student.com",
    "mentor_email": "kavita@mentor.com",
    "status": "active"
  },
  {
    "student_email": "divya_student@student.com",
    "mentor_email": "amit@mentor.com",
    "status": "active"
  }
]
